<?xml version="1.0" encoding="UTF-8" standalone="yes"?><Hotwire><Errors/><MetaData><CarMetaData><CarTypes><CarType><TypicalSeating>2 adults, 2 children</TypicalSeating><CarTypeName>Compact</CarTypeName><CarTypeCode>CCAR</CarTypeCode><PossibleFeatures>Automatic Transmission, Power Steering, Air Conditioning, Air Bags, AM/FM Stereo</PossibleFeatures><PossibleModels>Nissan Versa, Toyota Yaris, or similar</PossibleModels></CarType><CarType><TypicalSeating>2 adults, 2 children</TypicalSeating><CarTypeName>Economy</CarTypeName><CarTypeCode>ECAR</CarTypeCode><PossibleFeatures>Automatic Transmission, Air Conditioning, Air Bags, AM/FM Stereo</PossibleFeatures><PossibleModels>Chevy Aveo, Hyundai Accent, or similar</PossibleModels></CarType><CarType><TypicalSeating>5 adults</TypicalSeating><CarTypeName>Full Size</CarTypeName><CarTypeCode>FCAR</CarTypeCode><PossibleFeatures>Automatic Transmission, Power Steering, Air Conditioning, Air Bags, Anti-Lock Brakes, Cruise Control, AM/FM Stereo</PossibleFeatures><PossibleModels>Chevy Impala, Hyundai Sonata, or similar</PossibleModels></CarType><CarType><TypicalSeating>7 adults</TypicalSeating><CarTypeName>Full Size SUV</CarTypeName><CarTypeCode>FFAR</CarTypeCode><PossibleFeatures>Automatic Transmission, Power Steering, Air Conditioning, Air Bags, Cruise Control, AM/FM Stereo, CD Player</PossibleFeatures><PossibleModels>Chevy Tahoe, Toyota Highlander, or similar</PossibleModels></CarType><CarType><TypicalSeating>4 adults</TypicalSeating><CarTypeName>Midsize</CarTypeName><CarTypeCode>ICAR</CarTypeCode><PossibleFeatures>Automatic Transmission, Power Steering, Air Conditioning, Air Bags, AM/FM Stereo</PossibleFeatures><PossibleModels>Toyota Corolla, Nissan Sentra, or similar</PossibleModels></CarType><CarType><TypicalSeating>4 adults</TypicalSeating><CarTypeName>Midsize SUV</CarTypeName><CarTypeCode>IFAR</CarTypeCode><PossibleFeatures>Automatic Transmission, Air Conditioning</PossibleFeatures><PossibleModels>Ford Escape, Toyota Rav4 or similar</PossibleModels></CarType><CarType><TypicalSeating>5 adults</TypicalSeating><CarTypeName>Luxury</CarTypeName><CarTypeCode>LCAR</CarTypeCode><PossibleFeatures>Automatic Transmission, Power Steering, Air Conditioning, Air Bags, Anti-Lock Brakes, Cruise Control, AM/FM Stereo, CD Player</PossibleFeatures><PossibleModels>Lincoln Town Car, Cadillac DTS, or similar</PossibleModels></CarType><CarType><TypicalSeating>7 adults</TypicalSeating><CarTypeName>Minivan</CarTypeName><CarTypeCode>MVAR</CarTypeCode><PossibleFeatures>Automatic Transmission, Power Steering, Air Conditioning, Air Bags, Anti-Lock Brakes, Cruise Control, AM/FM Stereo</PossibleFeatures><PossibleModels>Dodge Grand Caravan or similar</PossibleModels></CarType><CarType><TypicalSeating>5 adults</TypicalSeating><CarTypeName>Premium</CarTypeName><CarTypeCode>PCAR</CarTypeCode><PossibleFeatures>Automatic Transmission, Power Steering, Air Conditioning, Air Bags, Anti-Lock Brakes, Cruise Control, AM/FM Stereo, CD Player</PossibleFeatures><PossibleModels>Ford Crown Victoria, Buick Lucerne, or similar</PossibleModels></CarType><CarType><TypicalSeating>2 adults, 2 children</TypicalSeating><CarTypeName>Standard</CarTypeName><CarTypeCode>SCAR</CarTypeCode><PossibleFeatures>Automatic Transmission, Power Steering, Air Conditioning, Air Bags, Anti-Lock Brakes, AM/FM Stereo</PossibleFeatures><PossibleModels>Ford Fusion, Chrysler Sebring, or similar</PossibleModels></CarType><CarType><TypicalSeating>5 adults</TypicalSeating><CarTypeName>Standard SUV</CarTypeName><CarTypeCode>SFAR</CarTypeCode><PossibleFeatures>Automatic Transmission, Power Steering, Air Conditioning, Air Bags, Anti-Lock Brakes, Cruise Control, AM/FM Stereo, CD Player</PossibleFeatures><PossibleModels>Jeep Grand Cherokee or similar</PossibleModels></CarType><CarType><TypicalSeating>4 adults</TypicalSeating><CarTypeName>Standard Pickup truck</CarTypeName><CarTypeCode>SPAR</CarTypeCode><PossibleFeatures>Automatic Transmission, Power Steering, Air Conditioning, Air Bags, Cruise Control, Anti-Lock Brakes, AM/FM Stereo</PossibleFeatures><PossibleModels>Chevy Colorado or similar</PossibleModels></CarType><CarType><TypicalSeating>4 adults</TypicalSeating><CarTypeName>Convertible</CarTypeName><CarTypeCode>STAR</CarTypeCode><PossibleFeatures>Automatic Transmission, Power Steering, Air Conditioning, Air Bags, Cruise Control, Anti-Lock Brakes, AM/FM Stereo</PossibleFeatures><PossibleModels>Ford Mustang, Chrysler Sebring,  or similar</PossibleModels></CarType><CarType><TypicalSeating>4 adults or more</TypicalSeating><CarTypeName>Special car</CarTypeName><CarTypeCode>XXAR</CarTypeCode><PossibleFeatures>Automatic Transmission, Air Conditioning, Air Bags, AM/FM Stereo</PossibleFeatures><PossibleModels>Compact size or larger but priced low like a compact</PossibleModels></CarType></CarTypes></CarMetaData></MetaData><Result><CarResult><CurrencyCode>USD</CurrencyCode><DeepLink>http://www.hotwire.com/car/deeplink-details.jsp?resultId=ODI4NTcwNTExMjozODU4ODMxODUxMTI-&amp;useCluster=4&amp;sid=S001&amp;bid=B001&amp;inputId=api-results&amp;actionType=303&amp;useCluster=4</DeepLink><ResultId>ODI4NTcwNTExMjozODU4ODMxODUxMTI-&amp;useCluster=4</ResultId><HWRefNumber>4853729640</HWRefNumber><SubTotal>10.72</SubTotal><TaxesAndFees>10.01</TaxesAndFees><TotalPrice>20.73</TotalPrice><CarTypeCode>XXAR</CarTypeCode><DailyRate>10.72</DailyRate><DropoffDay>12/12/2014</DropoffDay><DropoffTime>01:30</DropoffTime><PickupDay>12/11/2014</PickupDay><PickupTime>12:00</PickupTime><LocationDescription>On Airport - Shuttle to Vendor</LocationDescription><MileageDescription>Unlimited</MileageDescription><PickupAirport>SJC</PickupAirport><RentalDays>1</RentalDays></CarResult><CarResult><CurrencyCode>USD</CurrencyCode><DeepLink>http://www.hotwire.com/car/deeplink-details.jsp?resultId=ODI4NTcwNTExMjozODU4ODMxODUwNjY-&amp;useCluster=4&amp;sid=S001&amp;bid=B001&amp;inputId=api-results&amp;actionType=303&amp;useCluster=4</DeepLink><ResultId>ODI4NTcwNTExMjozODU4ODMxODUwNjY-&amp;useCluster=4</ResultId><HWRefNumber>3849533496</HWRefNumber><SubTotal>11.07</SubTotal><TaxesAndFees>10.10</TaxesAndFees><TotalPrice>21.17</TotalPrice><CarTypeCode>FCAR</CarTypeCode><DailyRate>11.07</DailyRate><DropoffDay>12/12/2014</DropoffDay><DropoffTime>01:30</DropoffTime><PickupDay>12/11/2014</PickupDay><PickupTime>12:00</PickupTime><LocationDescription>On Airport - Shuttle to Vendor</LocationDescription><MileageDescription>Unlimited</MileageDescription><PickupAirport>SJC</PickupAirport><RentalDays>1</RentalDays></CarResult><CarResult><CurrencyCode>USD</CurrencyCode><DeepLink>http://www.hotwire.com/car/deeplink-details.jsp?resultId=ODI4NTcwNTExMjozODU4ODMxODUwNzA-&amp;useCluster=4&amp;sid=S001&amp;bid=B001&amp;inputId=api-results&amp;actionType=303&amp;useCluster=4</DeepLink><ResultId>ODI4NTcwNTExMjozODU4ODMxODUwNzA-&amp;useCluster=4</ResultId><HWRefNumber>3714350502</HWRefNumber><SubTotal>7.95</SubTotal><TaxesAndFees>15.79</TaxesAndFees><TotalPrice>23.74</TotalPrice><CarTypeCode>ECAR</CarTypeCode><DailyRate>7.95</DailyRate><DropoffDay>12/12/2014</DropoffDay><DropoffTime>01:30</DropoffTime><PickupDay>12/11/2014</PickupDay><PickupTime>12:00</PickupTime><LocationDescription>On Airport - Shuttle to Vendor</LocationDescription><MileageDescription>Unlimited</MileageDescription><PickupAirport>SJC</PickupAirport><RentalDays>1</RentalDays></CarResult><CarResult><CurrencyCode>USD</CurrencyCode><DeepLink>http://www.hotwire.com/car/deeplink-details.jsp?resultId=ODI4NTcwNTExMjozODU4ODMxODUwNDg-&amp;useCluster=4&amp;sid=S001&amp;bid=B001&amp;inputId=api-results&amp;actionType=303&amp;useCluster=4</DeepLink><ResultId>ODI4NTcwNTExMjozODU4ODMxODUwNDg-&amp;useCluster=4</ResultId><HWRefNumber>4042502224</HWRefNumber><SubTotal>8.95</SubTotal><TaxesAndFees>15.92</TaxesAndFees><TotalPrice>24.87</TotalPrice><CarTypeCode>CCAR</CarTypeCode><DailyRate>8.95</DailyRate><DropoffDay>12/12/2014</DropoffDay><DropoffTime>01:30</DropoffTime><PickupDay>12/11/2014</PickupDay><PickupTime>12:00</PickupTime><LocationDescription>On Airport - Shuttle to Vendor</LocationDescription><MileageDescription>Unlimited</MileageDescription><PickupAirport>SJC</PickupAirport><RentalDays>1</RentalDays></CarResult><CarResult><CurrencyCode>USD</CurrencyCode><DeepLink>http://www.hotwire.com/car/deeplink-details.jsp?resultId=ODI4NTcwNTExMjozODU4ODMxODUwNjI-&amp;useCluster=4&amp;sid=S001&amp;bid=B001&amp;inputId=api-results&amp;actionType=303&amp;useCluster=4</DeepLink><ResultId>ODI4NTcwNTExMjozODU4ODMxODUwNjI-&amp;useCluster=4</ResultId><HWRefNumber>4669694708</HWRefNumber><SubTotal>8.95</SubTotal><TaxesAndFees>16.05</TaxesAndFees><TotalPrice>25.00</TotalPrice><CarTypeCode>ICAR</CarTypeCode><DailyRate>8.95</DailyRate><DropoffDay>12/12/2014</DropoffDay><DropoffTime>01:30</DropoffTime><PickupDay>12/11/2014</PickupDay><PickupTime>12:00</PickupTime><LocationDescription>On Airport - Shuttle to Vendor</LocationDescription><MileageDescription>Unlimited</MileageDescription><PickupAirport>SJC</PickupAirport><RentalDays>1</RentalDays></CarResult><CarResult><CurrencyCode>USD</CurrencyCode><DeepLink>http://www.hotwire.com/car/deeplink-details.jsp?resultId=ODI4NTcwNTExMjozODU4ODMxODUwNTk-&amp;useCluster=4&amp;sid=S001&amp;bid=B001&amp;inputId=api-results&amp;actionType=303&amp;useCluster=4</DeepLink><ResultId>ODI4NTcwNTExMjozODU4ODMxODUwNTk-&amp;useCluster=4</ResultId><HWRefNumber>4781845110</HWRefNumber><SubTotal>10.95</SubTotal><TaxesAndFees>16.64</TaxesAndFees><TotalPrice>27.59</TotalPrice><CarTypeCode>SCAR</CarTypeCode><DailyRate>10.95</DailyRate><DropoffDay>12/12/2014</DropoffDay><DropoffTime>01:30</DropoffTime><PickupDay>12/11/2014</PickupDay><PickupTime>12:00</PickupTime><LocationDescription>On Airport - Shuttle to Vendor</LocationDescription><MileageDescription>Unlimited</MileageDescription><PickupAirport>SJC</PickupAirport><RentalDays>1</RentalDays></CarResult><CarResult><CurrencyCode>USD</CurrencyCode><DeepLink>http://www.hotwire.com/car/deeplink-details.jsp?resultId=ODI4NTcwNTExMjozODU4ODMxODUxMTc-&amp;useCluster=4&amp;sid=S001&amp;bid=B001&amp;inputId=api-results&amp;actionType=303&amp;useCluster=4</DeepLink><ResultId>ODI4NTcwNTExMjozODU4ODMxODUxMTc-&amp;useCluster=4</ResultId><HWRefNumber>4667844392</HWRefNumber><SubTotal>27.95</SubTotal><TaxesAndFees>21.97</TaxesAndFees><TotalPrice>49.92</TotalPrice><CarTypeCode>MVAR</CarTypeCode><DailyRate>27.95</DailyRate><DropoffDay>12/12/2014</DropoffDay><DropoffTime>01:30</DropoffTime><PickupDay>12/11/2014</PickupDay><PickupTime>12:00</PickupTime><LocationDescription>On Airport - Shuttle to Vendor</LocationDescription><MileageDescription>Unlimited</MileageDescription><PickupAirport>SJC</PickupAirport><RentalDays>1</RentalDays></CarResult><CarResult><CurrencyCode>USD</CurrencyCode><DeepLink>http://www.hotwire.com/car/deeplink-details.jsp?resultId=ODI4NTcwNTExMjozODU4ODMxODUxMzA-&amp;useCluster=4&amp;sid=S001&amp;bid=B001&amp;inputId=api-results&amp;actionType=303&amp;useCluster=4</DeepLink><ResultId>ODI4NTcwNTExMjozODU4ODMxODUxMzA-&amp;useCluster=4</ResultId><HWRefNumber>4046558430</HWRefNumber><SubTotal>28.95</SubTotal><TaxesAndFees>22.11</TaxesAndFees><TotalPrice>51.06</TotalPrice><CarTypeCode>IFAR</CarTypeCode><DailyRate>28.95</DailyRate><DropoffDay>12/12/2014</DropoffDay><DropoffTime>01:30</DropoffTime><PickupDay>12/11/2014</PickupDay><PickupTime>12:00</PickupTime><LocationDescription>On Airport - Shuttle to Vendor</LocationDescription><MileageDescription>Unlimited</MileageDescription><PickupAirport>SJC</PickupAirport><RentalDays>1</RentalDays></CarResult><CarResult><CurrencyCode>USD</CurrencyCode><DeepLink>http://www.hotwire.com/car/deeplink-details.jsp?resultId=ODI4NTcwNTExMjozODU4ODMxODUwOTE-&amp;useCluster=4&amp;sid=S001&amp;bid=B001&amp;inputId=api-results&amp;actionType=303&amp;useCluster=4</DeepLink><ResultId>ODI4NTcwNTExMjozODU4ODMxODUwOTE-&amp;useCluster=4</ResultId><HWRefNumber>4468774207</HWRefNumber><SubTotal>37.95</SubTotal><TaxesAndFees>25.01</TaxesAndFees><TotalPrice>62.96</TotalPrice><CarTypeCode>PCAR</CarTypeCode><DailyRate>37.95</DailyRate><DropoffDay>12/12/2014</DropoffDay><DropoffTime>01:30</DropoffTime><PickupDay>12/11/2014</PickupDay><PickupTime>12:00</PickupTime><LocationDescription>On Airport - Shuttle to Vendor</LocationDescription><MileageDescription>Unlimited</MileageDescription><PickupAirport>SJC</PickupAirport><RentalDays>1</RentalDays></CarResult><CarResult><CurrencyCode>USD</CurrencyCode><DeepLink>http://www.hotwire.com/car/deeplink-details.jsp?resultId=ODI4NTcwNTExMjozODU4ODMxODUxMTA-&amp;useCluster=4&amp;sid=S001&amp;bid=B001&amp;inputId=api-results&amp;actionType=303&amp;useCluster=4</DeepLink><ResultId>ODI4NTcwNTExMjozODU4ODMxODUxMTA-&amp;useCluster=4</ResultId><HWRefNumber>3405438340</HWRefNumber><SubTotal>42.95</SubTotal><TaxesAndFees>26.44</TaxesAndFees><TotalPrice>69.39</TotalPrice><CarTypeCode>SFAR</CarTypeCode><DailyRate>42.95</DailyRate><DropoffDay>12/12/2014</DropoffDay><DropoffTime>01:30</DropoffTime><PickupDay>12/11/2014</PickupDay><PickupTime>12:00</PickupTime><LocationDescription>On Airport - Shuttle to Vendor</LocationDescription><MileageDescription>Unlimited</MileageDescription><PickupAirport>SJC</PickupAirport><RentalDays>1</RentalDays></CarResult><CarResult><CurrencyCode>USD</CurrencyCode><DeepLink>http://www.hotwire.com/car/deeplink-details.jsp?resultId=ODI4NTcwNTExMjozODU4ODMxODUwNTI-&amp;useCluster=4&amp;sid=S001&amp;bid=B001&amp;inputId=api-results&amp;actionType=303&amp;useCluster=4</DeepLink><ResultId>ODI4NTcwNTExMjozODU4ODMxODUwNTI-&amp;useCluster=4</ResultId><HWRefNumber>3829766524</HWRefNumber><SubTotal>53.95</SubTotal><TaxesAndFees>26.39</TaxesAndFees><TotalPrice>80.34</TotalPrice><CarTypeCode>SPAR</CarTypeCode><DailyRate>53.95</DailyRate><DropoffDay>12/12/2014</DropoffDay><DropoffTime>01:30</DropoffTime><PickupDay>12/11/2014</PickupDay><PickupTime>12:00</PickupTime><LocationDescription>On Airport - Shuttle to Vendor</LocationDescription><MileageDescription>Unlimited</MileageDescription><PickupAirport>SJC</PickupAirport><RentalDays>1</RentalDays></CarResult><CarResult><CurrencyCode>USD</CurrencyCode><DeepLink>http://www.hotwire.com/car/deeplink-details.jsp?resultId=ODI4NTcwNTExMjozODU4ODMxODUwNzY-&amp;useCluster=4&amp;sid=S001&amp;bid=B001&amp;inputId=api-results&amp;actionType=303&amp;useCluster=4</DeepLink><ResultId>ODI4NTcwNTExMjozODU4ODMxODUwNzY-&amp;useCluster=4</ResultId><HWRefNumber>4305157600</HWRefNumber><SubTotal>55.95</SubTotal><TaxesAndFees>30.45</TaxesAndFees><TotalPrice>86.40</TotalPrice><CarTypeCode>FFAR</CarTypeCode><DailyRate>55.95</DailyRate><DropoffDay>12/12/2014</DropoffDay><DropoffTime>01:30</DropoffTime><PickupDay>12/11/2014</PickupDay><PickupTime>12:00</PickupTime><LocationDescription>On Airport - Shuttle to Vendor</LocationDescription><MileageDescription>Unlimited</MileageDescription><PickupAirport>SJC</PickupAirport><RentalDays>1</RentalDays></CarResult><CarResult><CurrencyCode>USD</CurrencyCode><DeepLink>http://www.hotwire.com/car/deeplink-details.jsp?resultId=ODI4NTcwNTExMjozODU4ODMxODUwOTg-&amp;useCluster=4&amp;sid=S001&amp;bid=B001&amp;inputId=api-results&amp;actionType=303&amp;useCluster=4</DeepLink><ResultId>ODI4NTcwNTExMjozODU4ODMxODUwOTg-&amp;useCluster=4</ResultId><HWRefNumber>4412981827</HWRefNumber><SubTotal>100.00</SubTotal><TaxesAndFees>30.93</TaxesAndFees><TotalPrice>130.93</TotalPrice><CarTypeCode>STAR</CarTypeCode><DailyRate>100.00</DailyRate><DropoffDay>12/12/2014</DropoffDay><DropoffTime>01:30</DropoffTime><PickupDay>12/11/2014</PickupDay><PickupTime>12:00</PickupTime><LocationDescription>On Airport - Shuttle to Vendor</LocationDescription><MileageDescription>Unlimited</MileageDescription><PickupAirport>SJC</PickupAirport><RentalDays>1</RentalDays></CarResult><CarResult><CurrencyCode>USD</CurrencyCode><DeepLink>http://www.hotwire.com/car/deeplink-details.jsp?resultId=ODI4NTcwNTExMjozODU4ODMxODUxMTM-&amp;useCluster=4&amp;sid=S001&amp;bid=B001&amp;inputId=api-results&amp;actionType=303&amp;useCluster=4</DeepLink><ResultId>ODI4NTcwNTExMjozODU4ODMxODUxMTM-&amp;useCluster=4</ResultId><HWRefNumber>3142228203</HWRefNumber><SubTotal>125.10</SubTotal><TaxesAndFees>36.81</TaxesAndFees><TotalPrice>161.91</TotalPrice><CarTypeCode>LCAR</CarTypeCode><DailyRate>125.10</DailyRate><DropoffDay>12/12/2014</DropoffDay><DropoffTime>01:30</DropoffTime><PickupDay>12/11/2014</PickupDay><PickupTime>12:00</PickupTime><LocationDescription>On Airport - Shuttle to Vendor</LocationDescription><MileageDescription>Unlimited</MileageDescription><PickupAirport>SJC</PickupAirport><RentalDays>1</RentalDays></CarResult></Result><StatusCode>0</StatusCode><StatusDesc>success</StatusDesc></Hotwire>